{"team":{"0":{"id":669,"name":"Coleraine FC","logo":"https:\/\/media.api-sports.io\/football\/teams\/669.png","colors":null},"1":{"id":256,"name":"Motherwell","logo":"https:\/\/media.api-sports.io\/football\/teams\/256.png","colors":null}},"coach":{"0":{"id":1570,"name":"O. Kearney","photo":"https:\/\/media.api-sports.io\/football\/coachs\/1570.png"},"1":{"id":2400,"name":"S. Robinson","photo":"https:\/\/media.api-sports.io\/football\/coachs\/2400.png"}},"formation":{"0":"4-1-4-1","1":"4-3-3"},"startXI":{"0":[{"player":{"id":105648,"name":"G. Deane","number":1,"pos":"G","grid":"1:1"}},{"player":{"id":105929,"name":"A. Traynor","number":18,"pos":"M","grid":"2:4"}},{"player":{"id":105927,"name":"G. McConaghie","number":13,"pos":"D","grid":"2:3"}},{"player":{"id":105928,"name":"S. O'Donnell","number":15,"pos":"D","grid":"2:2"}},{"player":{"id":128080,"name":"L. Kane","number":2,"pos":"D","grid":"2:1"}},{"player":{"id":105646,"name":"S. Lowry","number":8,"pos":"F","grid":"3:1"}},{"player":{"id":128081,"name":"J. Carson","number":11,"pos":"F","grid":"4:4"}},{"player":{"id":106036,"name":"B. Doherty","number":7,"pos":"F","grid":"4:3"}},{"player":{"id":128417,"name":"A. Jarvis","number":6,"pos":"M","grid":"4:2"}},{"player":{"id":105933,"name":"J. McLaughlin","number":9,"pos":"F","grid":"4:1"}},{"player":{"id":128091,"name":"S. Nixon","number":21,"pos":"F","grid":"5:1"}}],"1":[{"player":{"id":44910,"name":"T. Carson","number":1,"pos":"G","grid":"1:1"}},{"player":{"id":44941,"name":"D. Gallagher","number":31,"pos":"D","grid":"2:4"}},{"player":{"id":44783,"name":"S. O'Donnell","number":33,"pos":"D","grid":"2:3"}},{"player":{"id":44943,"name":"R. Lamie","number":4,"pos":"D","grid":"2:2"}},{"player":{"id":17491,"name":"N. McGinley","number":5,"pos":"D","grid":"2:1"}},{"player":{"id":18041,"name":"B. Mugabi","number":16,"pos":"D","grid":"3:3"}},{"player":{"id":45142,"name":"L. Polworth","number":19,"pos":"M","grid":"3:2"}},{"player":{"id":17377,"name":"M. O'Hara","number":7,"pos":"M","grid":"3:1"}},{"player":{"id":44922,"name":"A. Campbell","number":6,"pos":"M","grid":"4:3"}},{"player":{"id":44909,"name":"T. Watt","number":32,"pos":"F","grid":"4:2"}},{"player":{"id":17760,"name":"C. Lang","number":29,"pos":"F","grid":"4:1"}}]},"substitutes":{"0":[{"player":{"id":105525,"name":"J. Glackin","number":17,"pos":"M","grid":null}},{"player":{"id":105923,"name":"E. Bradley","number":10,"pos":"M","grid":null}},{"player":{"id":105924,"name":"I. Parkhill","number":16,"pos":"F","grid":null}},{"player":{"id":128074,"name":"C. Allen","number":19,"pos":"F","grid":null}},{"player":{"id":128119,"name":"M. Gallagher","number":20,"pos":"G","grid":null}},{"player":{"id":69331,"name":"E. Tweed","number":14,"pos":"M","grid":null}},{"player":{"id":105926,"name":"A. Mullan","number":3,"pos":"D","grid":null}}],"1":[{"player":{"id":87768,"name":"S. Seedorf","number":17,"pos":"F","grid":null}},{"player":{"id":45291,"name":"B. Maguire","number":15,"pos":"D","grid":null}},{"player":{"id":44926,"name":"J. Hastie","number":11,"pos":"M","grid":null}},{"player":{"id":20067,"name":"C. Long","number":99,"pos":"F","grid":null}},{"player":{"id":107095,"name":"R. MacIver","number":25,"pos":"F","grid":null}},{"player":{"id":44925,"name":"L. Grimshaw","number":2,"pos":"D","grid":null}},{"player":{"id":138357,"name":"P. Morrison","number":23,"pos":"G","grid":null}}]}}