{"team":{"0":{"id":10285,"name":"Colombia U20","logo":"https:\/\/media.api-sports.io\/football\/teams\/10285.png","colors":null},"1":{"id":10294,"name":"New Zealand U20","logo":"https:\/\/media.api-sports.io\/football\/teams\/10294.png","colors":null}},"coach":{"0":{"id":8188,"name":"A. Reyes","photo":"https:\/\/media.api-sports.io\/football\/coachs\/8188.png"},"1":{"id":8189,"name":"D. Buckingham","photo":"https:\/\/media.api-sports.io\/football\/coachs\/8189.png"}},"formation":{"0":null,"1":null},"startXI":{"0":[{"player":{"id":13278,"name":"K. Mier","number":13,"pos":null,"grid":null}},{"player":{"id":79371,"name":"A. Arroyo","number":4,"pos":null,"grid":null}},{"player":{"id":13283,"name":"C. Cuesta","number":2,"pos":null,"grid":null}},{"player":{"id":13289,"name":"A. Reyes","number":3,"pos":null,"grid":null}},{"player":{"id":80998,"name":"I. Angulo","number":7,"pos":null,"grid":null}},{"player":{"id":13385,"name":"A. Balanta","number":5,"pos":null,"grid":null}},{"player":{"id":13300,"name":"A. Perea","number":6,"pos":null,"grid":null}},{"player":{"id":13181,"name":"G. Carvajal","number":15,"pos":null,"grid":null}},{"player":{"id":47582,"name":"J. Hern\u00e1ndez","number":10,"pos":null,"grid":null}},{"player":{"id":37161,"name":"L. Sinisterra","number":11,"pos":null,"grid":null}},{"player":{"id":79167,"name":"B. Vera","number":16,"pos":null,"grid":null}}],"1":[{"player":{"id":36777,"name":"M. Woud","number":1,"pos":null,"grid":null}},{"player":{"id":44973,"name":"G. Stanger","number":2,"pos":null,"grid":null}},{"player":{"id":94344,"name":"N. Pijnaker","number":5,"pos":null,"grid":null}},{"player":{"id":94541,"name":"J. Bell","number":8,"pos":null,"grid":null}},{"player":{"id":6935,"name":"S. Singh","number":10,"pos":null,"grid":null}},{"player":{"id":6931,"name":"L. Cacace","number":13,"pos":null,"grid":null}},{"player":{"id":6932,"name":"C. Elliot","number":17,"pos":null,"grid":null}},{"player":{"id":94333,"name":"E. Just","number":7,"pos":null,"grid":null}},{"player":{"id":6937,"name":"G. Stensness","number":4,"pos":null,"grid":null}},{"player":{"id":94322,"name":"C. McCowatt","number":19,"pos":null,"grid":null}},{"player":{"id":6938,"name":"B. Waine","number":18,"pos":null,"grid":null}}]},"substitutes":{"0":[{"player":{"id":13691,"name":"J. Carbonero","number":20,"pos":null,"grid":null}},{"player":{"id":13685,"name":"J. Palma","number":14,"pos":null,"grid":null}},{"player":{"id":13247,"name":"A. Amaya","number":18,"pos":null,"grid":null}},{"player":{"id":59414,"name":"L. Sandoval","number":9,"pos":null,"grid":null}},{"player":{"id":59390,"name":"R. Fontalvo","number":1,"pos":null,"grid":null}},{"player":{"id":59647,"name":"J. Lemus","number":12,"pos":null,"grid":null}},{"player":{"id":13408,"name":"D. Caicedo","number":17,"pos":null,"grid":null}},{"player":{"id":13493,"name":"C. Ter\u00e1n","number":19,"pos":null,"grid":null}},{"player":{"id":59519,"name":"J. Colorado","number":21,"pos":null,"grid":null}}],"1":[{"player":{"id":94380,"name":"M. Mata","number":9,"pos":null,"grid":null}},{"player":{"id":39029,"name":"M. Conroy","number":11,"pos":null,"grid":null}},{"player":{"id":94332,"name":"D. Wilkins","number":3,"pos":null,"grid":null}},{"player":{"id":39024,"name":"D. Schnell","number":6,"pos":null,"grid":null}},{"player":{"id":38826,"name":"C. Brown","number":12,"pos":null,"grid":null}},{"player":{"id":94379,"name":"L. Van Den Hoven","number":14,"pos":null,"grid":null}},{"player":{"id":94331,"name":"D. Wooldridge","number":16,"pos":null,"grid":null}},{"player":{"id":77179,"name":"W. Ebbinge","number":20,"pos":null,"grid":null}},{"player":{"id":94350,"name":"Z. Jones","number":21,"pos":null,"grid":null}}]}}